en16931/__init__.py
en16931/b2brouter.py
en16931/bank_info.py
en16931/entity.py
en16931/invoice.py
en16931/invoice_line.py
en16931/money.py
en16931/postal_address.py
en16931/tax.py
en16931/utils.py
en16931/validex.py
en16931/xpaths.py
en16931/templates/invoice.xml
en16931/tests/__init__.py
en16931/tests/conftest.py
en16931/tests/test_bank_info.py
en16931/tests/test_entity.py
en16931/tests/test_import_invoices.py
en16931/tests/test_invoice.py
en16931/tests/test_invoice_line.py
en16931/tests/test_tax.py
en16931-0.2.dist-info/LICENSE.txt
en16931-0.2.dist-info/METADATA
en16931-0.2.dist-info/WHEEL
en16931-0.2.dist-info/top_level.txt
en16931-0.2.dist-info/RECORD
