Metadata-Version: 2.1
Name: en16931
Version: 0.2
Summary: A Python 3 package to parse, generate and manage the EN16931 Invoice format
Home-page: https://github.com/invinet/python-en16931
Author: Invinet Sistemes
Author-email: jtorrents@ingent.net
Classifier: Development Status :: 4 - Beta
Classifier: Programming Language :: Python :: 3
Classifier: License :: OSI Approved :: Apache Software License
Classifier: Operating System :: OS Independent
License-File: LICENSE.txt
Requires-Dist: requests
Requires-Dist: py-money
Requires-Dist: Jinja2
Requires-Dist: lxml
